{"index.md":"e01a05b2","pinia_index.md":"8d351151","project_consult-order.md":"aaee35a8","project_consult.md":"b1cf90f9","project_end.md":"6a3fc8e8","project_home.md":"93423839","project_index.md":"d6a1b351","project_login.md":"2019702e","project_order.md":"11114f3e","project_room.md":"2c950880","project_super-doctor.md":"6fbd04c5","project_user.md":"857fa714","ts_backup.md":"3552c84d","ts_case.md":"9b48157d","ts_core.md":"42b9b02b","ts_index.md":"2b2fad4d","ts_pro.md":"45520d11","vue_case.md":"559e159d","vue_composition.md":"aa6d1f27","vue_index.md":"21748b47"}
