{"index.md":"055295a4","pinia_index.md":"ebadc248","project_address.md":"a0872c25","project_consult-order.md":"1ba24bda","project_consult.md":"276de4f6","project_end.md":"d0f84504","project_home.md":"74d67d7b","project_index.md":"684808b9","project_login.md":"2ae530bd","project_order.md":"0975a18f","project_room.md":"4197179f","project_super-doctor.md":"a487296a","project_user.md":"86a7c627","ts_backup.md":"f247783f","ts_case.md":"317658d2","ts_core.md":"32cc7cfd","ts_index.md":"12282e54","ts_pro.md":"7c04eb99","vue_case.md":"4d245e36","vue_composition.md":"6165784a","vue_index.md":"9c5e86e8"}
