{"index.md":"f6104ca7","pinia_index.md":"1f6fcfbf","project_address.md":"9c763701","project_consult-order.md":"870fb4c7","project_consult.md":"d6a3509b","project_end.md":"f4010ab4","project_home.md":"07889849","project_index.md":"c71953d1","project_login.md":"4a5aba5d","project_order.md":"44fc65c5","project_room.md":"4dace3b5","project_super-doctor.md":"86d4cee7","project_user.md":"ed17d795","ts_backup.md":"ca5df25a","ts_case.md":"5549030b","ts_core.md":"f2838e9b","ts_index.md":"fc563dfa","ts_pro.md":"37ee4588","vue_case.md":"a1e3cc1f","vue_composition.md":"d6779110","vue_index.md":"5e66e526"}
