{"index.md":"3dfe7bcf","pinia_index.md":"a87f8f78","project_address.md":"2f7ce7cb","project_consult-order.md":"7db08ff0","project_consult.md":"464983a9","project_end.md":"0b1a59a2","project_home.md":"9ba30bd7","project_index.md":"c81423fe","project_login.md":"92815151","project_order.md":"f582af32","project_room.md":"4cdc0be0","project_super-doctor.md":"4c25516f","project_user.md":"9f0e73fb","ts_backup.md":"009b39a6","ts_case.md":"fd04a63e","ts_core.md":"a36b0a29","ts_index.md":"3eba7f45","ts_pro.md":"6c3dbe00","vue_case.md":"7042a2bb","vue_composition.md":"2ed7b454","vue_index.md":"44317217"}
